evoclearn/rec/__init__.py
evoclearn/rec/ac2vec.py
evoclearn/rec/collect.py
evoclearn/rec/compile_model.py
evoclearn/rec/timit_cv.py
evoclearn/rec/train.py
evoclearn/rec/vec2sym.py
evoclearn/rec/version.py
evoclearn/rec/cli/__init__.py
evoclearn_rec-0.5.3.dist-info/LICENSE
evoclearn_rec-0.5.3.dist-info/METADATA
evoclearn_rec-0.5.3.dist-info/WHEEL
evoclearn_rec-0.5.3.dist-info/entry_points.txt
evoclearn_rec-0.5.3.dist-info/top_level.txt
evoclearn_rec-0.5.3.dist-info/RECORD
