Metadata-Version: 2.1
Name: evoclearn-rec
Version: 0.5.3
Summary: Syllable recogniser for Early Vocal Learning simulation models.
Home-page: https://gitlab.com/evoc-learn-group/evoc-learn-rec
Author: The EVocLearn Group
Author-email: daniel.r.vanniekerk@gmail.com
License: UNKNOWN
Platform: UNKNOWN
Requires-Python: >=3.7
Requires-Dist: click
Requires-Dist: dill (<0.4.0,>=0.3.4)
Requires-Dist: evoclearn-core (<0.19.0,>=0.18.5)
Requires-Dist: keras
Requires-Dist: pandas (<1.4.0,>=1.3.5)
Requires-Dist: tensorflow
Provides-Extra: dev
Requires-Dist: ipython ; extra == 'dev'
Requires-Dist: matplotlib ; extra == 'dev'
